stream_topic/__init__.py
stream_topic/__version__.py
stream_topic/NAM/NAM.py
stream_topic/NAM/__init__.py
stream_topic/commons/__init__.py
stream_topic/commons/check_steps.py
stream_topic/commons/load_steps.py
stream_topic/experimental/__init__.py
stream_topic/experimental/topic_poster.py
stream_topic/experimental/topic_story.py
stream_topic/experimental/topic_summary.py
stream_topic/metrics/TopwordEmbeddings.py
stream_topic/metrics/__init__.py
stream_topic/metrics/_helper_funcs.py
stream_topic/metrics/base.py
stream_topic/metrics/coherence_metrics.py
stream_topic/metrics/constants.py
stream_topic/metrics/diversity_metrics.py
stream_topic/metrics/intruder_metrics.py
stream_topic/metrics/metrics_config.py
stream_topic/models/CEDC.py
stream_topic/models/DCTE.py
stream_topic/models/KmeansTM.py
stream_topic/models/WordCluTM.py
stream_topic/models/__init__.py
stream_topic/models/bertopicTM.py
stream_topic/models/cbc.py
stream_topic/models/ctm.py
stream_topic/models/ctmneg.py
stream_topic/models/etm.py
stream_topic/models/lda.py
stream_topic/models/neurallda.py
stream_topic/models/nmf.py
stream_topic/models/nstm.py
stream_topic/models/prodlda.py
stream_topic/models/som.py
stream_topic/models/tntm.py
stream_topic/models/abstract_helper_models/__init__.py
stream_topic/models/abstract_helper_models/base.py
stream_topic/models/abstract_helper_models/inference_networks.py
stream_topic/models/abstract_helper_models/mixins.py
stream_topic/models/abstract_helper_models/neural_basemodel.py
stream_topic/models/neural_base_models/__init__.py
stream_topic/models/neural_base_models/ctm_base.py
stream_topic/models/neural_base_models/ctmneg_base.py
stream_topic/models/neural_base_models/etm_base.py
stream_topic/models/neural_base_models/neurallda_base.py
stream_topic/models/neural_base_models/nstm_base.py
stream_topic/models/neural_base_models/prodlda_base.py
stream_topic/models/neural_base_models/tntm_base.py
stream_topic/preprocessor/__init__.py
stream_topic/preprocessor/_cleaning.py
stream_topic-0.3.0.dist-info/LICENSE
stream_topic-0.3.0.dist-info/METADATA
stream_topic-0.3.0.dist-info/WHEEL
stream_topic-0.3.0.dist-info/top_level.txt
stream_topic-0.3.0.dist-info/RECORD
