Metadata-Version: 2.1
Name: stream-topic
Version: 0.3.0
Summary: A python package for expanded topic modeling and metrics
Home-page: https://github.com/AnFreTh/STREAM
Author: Anton Thielmann
Author-email: anton.thielmann@tu-clausthal.de
License: MIT
Project-URL: Documentation, https://stream.readthedocs.io/en/
Platform: UNKNOWN
Classifier: Programming Language :: Python :: 3
Classifier: License :: OSI Approved :: MIT License
Classifier: Operating System :: OS Independent
Requires-Python: >=3.6
Requires-Dist: numpy
Requires-Dist: pandas
Requires-Dist: scikit-learn
Requires-Dist: nltk
Requires-Dist: datasets
Requires-Dist: lightning
Requires-Dist: torch
Requires-Dist: sentence-transformers
Requires-Dist: transformers
Requires-Dist: gensim
Requires-Dist: umap-learn
Requires-Dist: community
Requires-Dist: networkx
Requires-Dist: python-louvain
Requires-Dist: langdetect
Requires-Dist: loguru
Requires-Dist: ipywidgets
Requires-Dist: ipykernel<6.22.0
Requires-Dist: optuna==3.6.1
Requires-Dist: optuna-integration==3.6.0
Requires-Dist: hanlp==2.1.1
Requires-Dist: jieba==0.42.1
Requires-Dist: OpenCC==1.1.9
Requires-Dist: snownlp==0.12.3
Requires-Dist: thulac==0.2.2
Requires-Dist: optuna
Requires-Dist: optuna-integration
Provides-Extra: bertopic
Requires-Dist: hdbscan; extra == "bertopic"
Provides-Extra: dcte
Requires-Dist: pyarrow; extra == "dcte"
Requires-Dist: setfit; extra == "dcte"
Provides-Extra: experimental
Requires-Dist: openai; extra == "experimental"
Provides-Extra: plotting
Requires-Dist: dash; extra == "plotting"
Requires-Dist: plotly; extra == "plotting"
Requires-Dist: matplotlib; extra == "plotting"
Requires-Dist: wordcloud; extra == "plotting"
